fairtally/__init__.py
fairtally/__version__.py
fairtally/check.py
fairtally/cli.py
fairtally/redirect_stdout_stderr.py
fairtally/utils.py
fairtally/data/index.html.template
fairtally-0.1.0.data/data/citation/fairtally/CITATION.cff
fairtally-0.1.0.dist-info/LICENSE
fairtally-0.1.0.dist-info/METADATA
fairtally-0.1.0.dist-info/NOTICE
fairtally-0.1.0.dist-info/WHEEL
fairtally-0.1.0.dist-info/entry_points.txt
fairtally-0.1.0.dist-info/top_level.txt
fairtally-0.1.0.dist-info/RECORD
