Metadata-Version: 2.1
Name: fairtally
Version: 0.1.0
Summary: Make a report based on howfairis results
Home-page: https://github.com/fair-software/fairtally
Author: FAIR Software
Author-email: j.spaaks@esciencecenter.nl
License: Apache Software License 2.0
Keywords: fairtally
Platform: UNKNOWN
Classifier: Development Status :: 2 - Pre-Alpha
Classifier: Intended Audience :: Developers
Classifier: License :: OSI Approved :: Apache Software License
Classifier: Natural Language :: English
Classifier: Programming Language :: Python :: 3
Classifier: Programming Language :: Python :: 3.6
Classifier: Programming Language :: Python :: 3.7
Classifier: Programming Language :: Python :: 3.8
Classifier: Programming Language :: Python :: 3.9
Requires-Dist: click (==7.*)
Requires-Dist: howfairis (==0.14.*)
Requires-Dist: tqdm (==4.*)
Provides-Extra: dev
Requires-Dist: bumpversion ; extra == 'dev'
Requires-Dist: prospector[with_pyroma] ; extra == 'dev'
Requires-Dist: pycodestyle ; extra == 'dev'
Requires-Dist: pytest-cov ; extra == 'dev'
Requires-Dist: pytest-runner ; extra == 'dev'
Requires-Dist: pytest ; extra == 'dev'
Requires-Dist: recommonmark ; extra == 'dev'
Requires-Dist: requests-mock ; extra == 'dev'
Requires-Dist: sphinx-rtd-theme ; extra == 'dev'
Requires-Dist: sphinx-click ; extra == 'dev'
Requires-Dist: sphinx ; extra == 'dev'
Requires-Dist: yapf ; extra == 'dev'
Provides-Extra: publishing
Requires-Dist: twine ; extra == 'publishing'
Requires-Dist: wheel ; extra == 'publishing'
